otlmow_postenmapping/MappingConverter.py
otlmow_postenmapping/PostAssetFactory.py
otlmow_postenmapping/PostenMappingDict.py
otlmow_postenmapping/PostenMappingTemplateModifier.py
otlmow_postenmapping/SQLDbReader.py
otlmow_postenmapping/__init__.py
otlmow_postenmapping/Exceptions/InvalidMappingKeyError.py
otlmow_postenmapping/Exceptions/MissingMappingKeyError.py
otlmow_postenmapping/Exceptions/MultipleMappingKeysError.py
otlmow_postenmapping/TypeTemplateORM/Base.py
otlmow_postenmapping/TypeTemplateORM/GeneralInfo.py
otlmow_postenmapping/TypeTemplateORM/TemplateMapping.py
otlmow_postenmapping-0.6.dist-info/LICENSE
otlmow_postenmapping-0.6.dist-info/METADATA
otlmow_postenmapping-0.6.dist-info/WHEEL
otlmow_postenmapping-0.6.dist-info/top_level.txt
otlmow_postenmapping-0.6.dist-info/RECORD
