Metadata-Version: 2.1
Name: otlmow_postenmapping
Version: 0.6
Author-email: David Vlaminck <david.vlaminck@mow.vlaanderen.be>
License:                     GNU GENERAL PUBLIC LICENSE
Project-URL: Homepage, https://github.com/davidvlaminck/OTLMOW-PostenMapping
Project-URL: Bug Tracker, https://github.com/davidvlaminck/OTLMOW-PostenMapping/issues
Classifier: Programming Language :: Python :: 3
Classifier: Programming Language :: Python :: 3.9
Classifier: Programming Language :: Python :: 3.10
Classifier: Programming Language :: Python :: 3.11
Classifier: Programming Language :: Python :: 3.12
Classifier: Programming Language :: Python :: 3.13
Classifier: Operating System :: OS Independent
Requires-Python: >=3.9
License-File: LICENSE
Requires-Dist: otlmow_converter>=1.5
Requires-Dist: sqlalchemy>=2.0.35
Requires-Dist: otlmow_template>=0.5
